status_map/__init__.py
status_map/exceptions.py
status_map-0.5.1.dist-info/LICENSE
status_map-0.5.1.dist-info/WHEEL
status_map-0.5.1.dist-info/METADATA
status_map-0.5.1.dist-info/RECORD
